openfisca_cote_d_ivoire/__init__.py
openfisca_cote_d_ivoire/entities.py
openfisca_cote_d_ivoire/input_data_builder.py
openfisca_cote_d_ivoire/survey_scenarios.py
openfisca_cote_d_ivoire/assets/definition_variables_micro_CIV.csv
openfisca_cote_d_ivoire/assets/recettes_fiscales_CIV.csv
openfisca_cote_d_ivoire/parameters/taxes/impot_revenu/abattement.yaml
openfisca_cote_d_ivoire/parameters/taxes/impot_revenu/bareme.yaml
openfisca_cote_d_ivoire/reforms/__init__.py
openfisca_cote_d_ivoire/tests/__init__.py
openfisca_cote_d_ivoire/tests/test_add_ceq_framework.py
openfisca_cote_d_ivoire/tests/test_aggregates.py
openfisca_cote_d_ivoire/tests/test_survey_scenario_from_stata_data.py
openfisca_cote_d_ivoire/tests/formulas/impot_general_revenu.yaml
openfisca_cote_d_ivoire/tests/formulas/nombre_de_parts.yaml
openfisca_cote_d_ivoire/variables/caracteristiques_socio_demographiques.py
openfisca_cote_d_ivoire/variables/consommation.py
openfisca_cote_d_ivoire/variables/revenus.py
openfisca_cote_d_ivoire/variables/weights.py
openfisca_cote_d_ivoire/variables/ceq/__init__.py
openfisca_cote_d_ivoire/variables/ceq/contributions.py
openfisca_cote_d_ivoire/variables/ceq/income.py
openfisca_cote_d_ivoire/variables/ceq/subsidies.py
openfisca_cote_d_ivoire/variables/ceq/taxes.py
openfisca_cote_d_ivoire/variables/ceq/transfers/__init__.py
openfisca_cote_d_ivoire/variables/ceq/transfers/cash_transfers.py
openfisca_cote_d_ivoire/variables/ceq/transfers/in_kind_transfers.py
openfisca_cote_d_ivoire/variables/prelevements_obligatoires/__init__.py
openfisca_cote_d_ivoire/variables/prelevements_obligatoires/impots_directs.py
openfisca_cote_d_ivoire/variables/prelevements_obligatoires/impots_indirects.py
openfisca_cote_d_ivoire/variables/prelevements_obligatoires/prelevements_sociaux.py
openfisca_cote_d_ivoire/variables/prestations/prestations_en_espece.py
openfisca_cote_d_ivoire/variables/prestations/prestations_en_nature.py
OpenFisca_COTE_D_IVOIRE-0.9.7.dist-info/LICENSE.AGPL.txt
OpenFisca_COTE_D_IVOIRE-0.9.7.dist-info/METADATA
OpenFisca_COTE_D_IVOIRE-0.9.7.dist-info/WHEEL
OpenFisca_COTE_D_IVOIRE-0.9.7.dist-info/top_level.txt
OpenFisca_COTE_D_IVOIRE-0.9.7.dist-info/RECORD
